odoo/addons/l10n_fi_edicode/README.rst
odoo/addons/l10n_fi_edicode/__init__.py
odoo/addons/l10n_fi_edicode/__manifest__.py
odoo/addons/l10n_fi_edicode/data/res_partner_operator_einvoice.xml
odoo/addons/l10n_fi_edicode/i18n/fi.po
odoo/addons/l10n_fi_edicode/i18n/l10n_fi_edicode.pot
odoo/addons/l10n_fi_edicode/models/__init__.py
odoo/addons/l10n_fi_edicode/models/res_partner.py
odoo/addons/l10n_fi_edicode/models/res_partner_operator_einvoice.py
odoo/addons/l10n_fi_edicode/security/ir.model.access.csv
odoo/addons/l10n_fi_edicode/static/description/icon.png
odoo/addons/l10n_fi_edicode/view/res_partner.xml
odoo12_addon_l10n_fi_edicode-12.0.1.0.0.99.dev3.dist-info/METADATA
odoo12_addon_l10n_fi_edicode-12.0.1.0.0.99.dev3.dist-info/RECORD
odoo12_addon_l10n_fi_edicode-12.0.1.0.0.99.dev3.dist-info/WHEEL
odoo12_addon_l10n_fi_edicode-12.0.1.0.0.99.dev3.dist-info/top_level.txt
